MANIFEST.in
README.rst
requirements-dev.txt
requirements.txt
setup.cfg
setup.py
tox.ini
flask_security/__init__.py
flask_security/changeable.py
flask_security/confirmable.py
flask_security/core.py
flask_security/datastore.py
flask_security/decorators.py
flask_security/forms.py
flask_security/passwordless.py
flask_security/recoverable.py
flask_security/registerable.py
flask_security/script.py
flask_security/signals.py
flask_security/utils.py
flask_security/views.py
flask_security/templates/security/_macros.html
flask_security/templates/security/_menu.html
flask_security/templates/security/_messages.html
flask_security/templates/security/change_password.html
flask_security/templates/security/forgot_password.html
flask_security/templates/security/login_user.html
flask_security/templates/security/register_user.html
flask_security/templates/security/reset_password.html
flask_security/templates/security/send_confirmation.html
flask_security/templates/security/send_login.html
flask_security/templates/security/email/change_notice.html
flask_security/templates/security/email/change_notice.txt
flask_security/templates/security/email/confirmation_instructions.html
flask_security/templates/security/email/confirmation_instructions.txt
flask_security/templates/security/email/login_instructions.html
flask_security/templates/security/email/login_instructions.txt
flask_security/templates/security/email/reset_instructions.html
flask_security/templates/security/email/reset_instructions.txt
flask_security/templates/security/email/reset_notice.html
flask_security/templates/security/email/reset_notice.txt
flask_security/templates/security/email/welcome.html
flask_security/templates/security/email/welcome.txt
quokka_flask_security.egg-info/PKG-INFO
quokka_flask_security.egg-info/SOURCES.txt
quokka_flask_security.egg-info/dependency_links.txt
quokka_flask_security.egg-info/not-zip-safe
quokka_flask_security.egg-info/requires.txt
quokka_flask_security.egg-info/top_level.txt
tests/conftest.py
tests/test_changeable.py
tests/test_common.py
tests/test_configuration.py
tests/test_confirmable.py
tests/test_context_processors.py
tests/test_datastore.py
tests/test_entities.py
tests/test_hashing.py
tests/test_misc.py
tests/test_passwordless.py
