Metadata-Version: 1.1
Name: quokka-flask-security
Version: 1.7.4
Summary: Fork of Simple security for Flask apps
Home-page: https://github.com/quokkaproject/flask-security
Author: Matt Wright
Author-email: matt@nobien.net
License: MIT
Platform: any
Classifier: Development Status :: 4 - Beta
Classifier: Environment :: Web Environment
Classifier: Intended Audience :: Developers
Classifier: License :: OSI Approved :: MIT License
Classifier: Operating System :: OS Independent
Classifier: Programming Language :: Python
Classifier: Topic :: Internet :: WWW/HTTP :: Dynamic Content
Classifier: Topic :: Software Development :: Libraries :: Python Modules
